megamicros/__init__.py
megamicros/exception.py
megamicros/geometry.py
megamicros/log.py
megamicros/mqtt.py
megamicros/muh5.py
megamicros/usb.py
megamicros/acoustics/__init__.py
megamicros/acoustics/bmf.py
megamicros/acoustics/omp.py
megamicros/acoustics/sgcal_ambient.py
megamicros/acoustics/sgcal_cov_gpu.py
megamicros/acoustics/sgcal_example.py
megamicros/apps/__init__.py
megamicros/apps/main.py
megamicros/apps/version.py
megamicros/core/__init__.py
megamicros/core/base.py
megamicros/core/mu.py
megamicros/data/__init__.py
megamicros/signal/__init__.py
megamicros-3.0.6.dist-info/licenses/LICENSE
megamicros-3.0.6.dist-info/METADATA
megamicros-3.0.6.dist-info/WHEEL
megamicros-3.0.6.dist-info/entry_points.txt
megamicros-3.0.6.dist-info/top_level.txt
megamicros-3.0.6.dist-info/RECORD
