Metadata-Version: 2.4
Name: megamicros
Version: 3.0.6
Summary: Megamicros Mems array library
Author-email: Bruno Gas <bruno.gas@bimea.io>
License: MIT
Project-URL: Homepage, https://github.com/bimea/megamicros
Project-URL: Documentation, https://readthedoc.bimea.io
Project-URL: Source, https://github.com/bimea/megamicros/
Keywords: MEMs,antenna,beamforming,acoustics,Machine Learninge
Classifier: Development Status :: 4 - Beta
Classifier: Intended Audience :: Developers
Classifier: Topic :: Software Development :: Build Tools
Classifier: License :: OSI Approved :: MIT License
Classifier: Programming Language :: Python
Classifier: Programming Language :: Python :: 3
Classifier: Programming Language :: Python :: 3 :: Only
Classifier: Programming Language :: Python :: 3.7
Classifier: Programming Language :: Python :: 3.8
Classifier: Programming Language :: Python :: 3.9
Classifier: Programming Language :: Python :: 3.10
Classifier: Programming Language :: Python :: 3.11
Classifier: Programming Language :: Python :: 3.12
Classifier: Programming Language :: Python :: Implementation :: CPython
Classifier: Programming Language :: Python :: Implementation :: PyPy
Requires-Python: >=3.7
License-File: LICENSE
Requires-Dist: numpy
Requires-Dist: scipy
Requires-Dist: matplotlib
Requires-Dist: libusb1
Requires-Dist: h5py
Requires-Dist: imageio
Dynamic: license-file
